qbitcoin/__init__.py
qbitcoin/_version.py
qbitcoin/cli.py
qbitcoin/grpcProxy.py
qbitcoin/install.py
qbitcoin/main.py
qbitcoin/measure.py
qbitcoin/smart_installer.py
qbitcoin/version.py
qbitcoin/core/AddressState.py
qbitcoin/core/Block.py
qbitcoin/core/BlockHeader.py
qbitcoin/core/BlockMetadata.py
qbitcoin/core/ChainManager.py
qbitcoin/core/DifficultyTracker.py
qbitcoin/core/ESyncState.py
qbitcoin/core/FalconHelper.py
qbitcoin/core/GenesisBlock.py
qbitcoin/core/Indexer.py
qbitcoin/core/LastTransactions.py
qbitcoin/core/Message.py
qbitcoin/core/MessageRequest.py
qbitcoin/core/Miner.py
qbitcoin/core/MultiSigAddressState.py
qbitcoin/core/OptimizedAddressState.py
qbitcoin/core/OutgoingMessage.py
qbitcoin/core/PaginatedBitfield.py
qbitcoin/core/PaginatedData.py
qbitcoin/core/PaginatedFalconPK.py
qbitcoin/core/PoWValidator.py
qbitcoin/core/ProposalRecord.py
qbitcoin/core/Singleton.py
qbitcoin/core/State.py
qbitcoin/core/StateContainer.py
qbitcoin/core/StateMigration.py
qbitcoin/core/TokenList.py
qbitcoin/core/TokenMetadata.py
qbitcoin/core/TransactionInfo.py
qbitcoin/core/TransactionMetadata.py
qbitcoin/core/TransactionPool.py
qbitcoin/core/VoteStats.py
qbitcoin/core/Wallet.py
qbitcoin/core/__init__.py
qbitcoin/core/config.py
qbitcoin/core/formulas.py
qbitcoin/core/genesis.yml
qbitcoin/core/messagereceipt.py
qbitcoin/core/node.py
qbitcoin/core/qbitnode.py
qbitcoin/core/miners/__init__.py
qbitcoin/core/miners/qrandomx/QRXMiner.py
qbitcoin/core/miners/qrandomx/QRXPoWValidator.py
qbitcoin/core/miners/qrandomx/__init__.py
qbitcoin/core/miners/qryptonight7/CNv1Miner.py
qbitcoin/core/miners/qryptonight7/CNv1PoWValidator.py
qbitcoin/core/miners/qryptonight7/__init__.py
qbitcoin/core/misc/DependencyChecker.py
qbitcoin/core/misc/__init__.py
qbitcoin/core/misc/db.py
qbitcoin/core/misc/expiring_set.py
qbitcoin/core/misc/helper.py
qbitcoin/core/misc/logger.py
qbitcoin/core/misc/logger_twisted.py
qbitcoin/core/misc/ntp.py
qbitcoin/core/misc/set_logger.py
qbitcoin-1.1.4.dist-info/licenses/LICENSE
qbitcoin-1.1.4.dist-info/METADATA
qbitcoin-1.1.4.dist-info/WHEEL
qbitcoin-1.1.4.dist-info/entry_points.txt
qbitcoin-1.1.4.dist-info/top_level.txt
qbitcoin-1.1.4.dist-info/RECORD
