Metadata-Version: 2.4
Name: qbitcoin
Version: 1.1.4
Summary: A Python-based cryptocurrency implementation with quantum-resistant features
Home-page: https://github.com/Hamza1s34/Qbitcoin
Author: Hamza
Author-email: Hamza <hamza@qbitcoin.dev>
License-Expression: MIT
Project-URL: Homepage, https://github.com/Hamza1s34/Qbitcoin
Project-URL: Repository, https://github.com/Hamza1s34/Qbitcoin
Project-URL: Issues, https://github.com/Hamza1s34/Qbitcoin/issues
Project-URL: Documentation, https://github.com/Hamza1s34/Qbitcoin
Keywords: cryptocurrency,blockchain,quantum-resistant,falcon,post-quantum
Classifier: Development Status :: 4 - Beta
Classifier: Intended Audience :: Developers
Classifier: Programming Language :: Python :: 3
Classifier: Programming Language :: Python :: 3.9
Classifier: Programming Language :: Python :: 3.10
Classifier: Programming Language :: Python :: 3.11
Classifier: Programming Language :: Python :: 3.12
Classifier: Topic :: Software Development :: Libraries :: Python Modules
Classifier: Topic :: Security :: Cryptography
Classifier: Topic :: Internet :: WWW/HTTP :: Dynamic Content
Requires-Python: >=3.8
License-File: LICENSE
Requires-Dist: plyvel>=1.5.0
Requires-Dist: ntplib>=0.4.0
Requires-Dist: Twisted>=22.0.0
Requires-Dist: colorlog>=6.0.0
Requires-Dist: simplejson>=3.17.0
Requires-Dist: PyYAML>=6.0
Requires-Dist: grpcio-tools>=1.50.0
Requires-Dist: grpcio>=1.50.0
Requires-Dist: google-api-python-client>=2.70.0
Requires-Dist: google-auth>=2.0.0
Requires-Dist: httplib2>=0.20.0
Requires-Dist: service_identity>=21.0.0
Requires-Dist: protobuf>=4.0.0
Requires-Dist: pyopenssl>=23.0.0
Requires-Dist: six>=1.16.0
Requires-Dist: click>=8.0.0
Requires-Dist: pqcrypto>=0.3.0
Requires-Dist: Flask>=2.0.0
Requires-Dist: json-rpc>=1.13.0
Requires-Dist: idna>=3.0
Requires-Dist: cryptography>=40.0.0
Requires-Dist: base58>=2.1.0
Requires-Dist: mock>=4.0.0
Requires-Dist: daemonize>=2.5.0
Provides-Extra: dev
Requires-Dist: pytest; extra == "dev"
Requires-Dist: pytest-cov; extra == "dev"
Requires-Dist: black; extra == "dev"
Requires-Dist: flake8; extra == "dev"
Requires-Dist: mypy; extra == "dev"
Dynamic: author
Dynamic: home-page
Dynamic: license-file
Dynamic: requires-python
